jupytercad_core/__init__.py
jupytercad_core/_version.py
jupytercad_core/handlers.py
jupytercad_core/jcad_ydoc.py
jupytercad_core/step_ydoc.py
jupytercad_core/stl_ydoc.py
jupytercad_core/schema/__init__.py
jupytercad_core/schema/interfaces/__init__.py
jupytercad_core/schema/interfaces/any.py
jupytercad_core/schema/interfaces/box.py
jupytercad_core/schema/interfaces/chamfer.py
jupytercad_core/schema/interfaces/cone.py
jupytercad_core/schema/interfaces/cut.py
jupytercad_core/schema/interfaces/cylinder.py
jupytercad_core/schema/interfaces/extrusion.py
jupytercad_core/schema/interfaces/fillet.py
jupytercad_core/schema/interfaces/fuse.py
jupytercad_core/schema/interfaces/geomCircle.py
jupytercad_core/schema/interfaces/geomLineSegment.py
jupytercad_core/schema/interfaces/intersection.py
jupytercad_core/schema/interfaces/jcad.py
jupytercad_core/schema/interfaces/placement.py
jupytercad_core/schema/interfaces/postOperator.py
jupytercad_core/schema/interfaces/sketch.py
jupytercad_core/schema/interfaces/sphere.py
jupytercad_core/schema/interfaces/torus.py
jupytercad_core-3.4.0.data/data/etc/jupyter/jupyter_server_config.d/jupytercad_core.json
jupytercad_core-3.4.0.data/data/share/jupyter/labextensions/@jupytercad/jupytercad-core/package.json
jupytercad_core-3.4.0.data/data/share/jupyter/labextensions/@jupytercad/jupytercad-core/schemas/@jupytercad/jupytercad-core/jupytercad-settings.json
jupytercad_core-3.4.0.data/data/share/jupyter/labextensions/@jupytercad/jupytercad-core/schemas/@jupytercad/jupytercad-core/package.json.orig
jupytercad_core-3.4.0.data/data/share/jupyter/labextensions/@jupytercad/jupytercad-core/static/201.33f5254e80b2347c754a.js
jupytercad_core-3.4.0.data/data/share/jupyter/labextensions/@jupytercad/jupytercad-core/static/413.9fc67e2541d86ea962a4.js
jupytercad_core-3.4.0.data/data/share/jupyter/labextensions/@jupytercad/jupytercad-core/static/426.c2ea37bc41f148b39a5f.js
jupytercad_core-3.4.0.dist-info/METADATA
jupytercad_core-3.4.0.dist-info/WHEEL
jupytercad_core-3.4.0.dist-info/entry_points.txt
jupytercad_core-3.4.0.dist-info/licenses/LICENSE
jupytercad_core-3.4.0.dist-info/RECORD
